dragons96_tools/__init__.py
dragons96_tools/base.py
dragons96_tools/env.py
dragons96_tools/algorithm/__init__.py
dragons96_tools/algorithm/similarity.py
dragons96_tools/builders/__init__.py
dragons96_tools/builders/base.py
dragons96_tools/builders/html.py
dragons96_tools/builders/markdown.py
dragons96_tools/cache/__init__.py
dragons96_tools/cache/cache.py
dragons96_tools/cache/ext/__init__.py
dragons96_tools/cache/ext/sqlite.py
dragons96_tools/clickhouse/__init__.py
dragons96_tools/clickhouse/clickhouse_driver.py
dragons96_tools/cryptography/__init__.py
dragons96_tools/cryptography/aes.py
dragons96_tools/cryptography/base.py
dragons96_tools/cryptography/base64.py
dragons96_tools/cryptography/hmac.py
dragons96_tools/cryptography/md5.py
dragons96_tools/exceptions/__init__.py
dragons96_tools/exceptions/base.py
dragons96_tools/fastapi/__init__.py
dragons96_tools/fastapi/base.py
dragons96_tools/files/__init__.py
dragons96_tools/files/base.py
dragons96_tools/files/csv.py
dragons96_tools/files/eval.py
dragons96_tools/files/excel.py
dragons96_tools/files/ini.py
dragons96_tools/files/json.py
dragons96_tools/files/properties.py
dragons96_tools/files/xml.py
dragons96_tools/files/yaml.py
dragons96_tools/func/__init__.py
dragons96_tools/func/ease.py
dragons96_tools/id/__init__.py
dragons96_tools/id/snowflake.py
dragons96_tools/impala/__init__.py
dragons96_tools/impala/impyla.py
dragons96_tools/ioc/__init__.py
dragons96_tools/ioc/base.py
dragons96_tools/ioc/constants.py
dragons96_tools/ioc/context.py
dragons96_tools/ioc/beans/__init__.py
dragons96_tools/ioc/beans/factory/__init__.py
dragons96_tools/ioc/beans/factory/base.py
dragons96_tools/ioc/beans/factory/initializing_bean.py
dragons96_tools/ioc/beans/factory/simple.py
dragons96_tools/ioc/beans/proxy/__init__.py
dragons96_tools/ioc/beans/proxy/base.py
dragons96_tools/ioc/beans/proxy/delay.py
dragons96_tools/ioc/boot/__init__.py
dragons96_tools/ioc/boot/base.py
dragons96_tools/ioc/config/__init__.py
dragons96_tools-0.0.48.dist-info/LICENSE
dragons96_tools-0.0.48.dist-info/METADATA
dragons96_tools-0.0.48.dist-info/WHEEL
dragons96_tools-0.0.48.dist-info/top_level.txt
dragons96_tools-0.0.48.dist-info/RECORD
